fastmodels/__init__.py
fastmodels/cli.py
fastmodels/datavalidator/__init__.py
fastmodels/datavalidator/validator.py
fastmodels/tests/__init__.py
fastmodels/tests/test_validator.py
fastmodels/utils/__init__.py
fastmodels/utils/modelclient.py
fastmodels/utils/validator.py
fastmodels-0.1.9.dist-info/METADATA
fastmodels-0.1.9.dist-info/WHEEL
fastmodels-0.1.9.dist-info/entry_points.txt
fastmodels-0.1.9.dist-info/top_level.txt
fastmodels-0.1.9.dist-info/RECORD
