Metadata-Version: 2.1
Name: fastmodels
Version: 0.1.9
Summary: A command-line interface for interacting with FastModel product and services.
Requires-Dist: jsonschema
Requires-Dist: requests
